{
  "id": "00000000-0000-0000-0000-000000000000",
  "prevId": "",
  "version": "7",
  "dialect": "postgresql",
  "tables": {
    "public.testimonials": {
      "name": "testimonials",
      "schema": "",
      "columns": {
        "id": {
          "name": "id",
          "type": "bigint",
          "primaryKey": true,
          "notNull": true,
          "identity": {
            "type": "byDefault",
            "name": "testimonials_id_seq",
            "increment": "1",
            "minValue": "1",
            "maxValue": "9223372036854775807",
            "startWith": "1",
            "cache": "1",
            "cycle": false,
            "schema": "public"
          }
        },
        "created_at": {
          "name": "created_at",
          "type": "timestamp with time zone",
          "primaryKey": false,
          "notNull": true,
          "default": "now()"
        },
        "full_name": {
          "name": "full_name",
          "type": "text",
          "primaryKey": false,
          "notNull": true
        },
        "company": {
          "name": "company",
          "type": "text",
          "primaryKey": false,
          "notNull": false
        },
        "occupation": {
          "name": "occupation",
          "type": "text",
          "primaryKey": false,
          "notNull": false
        },
        "review": {
          "name": "review",
          "type": "text",
          "primaryKey": false,
          "notNull": true
        },
        "rating": {
          "name": "rating",
          "type": "smallint",
          "primaryKey": false,
          "notNull": true
        },
        "approved": {
          "name": "approved",
          "type": "boolean",
          "primaryKey": false,
          "notNull": true,
          "default": false
        },
        "avatar": {
          "name": "avatar",
          "type": "text",
          "primaryKey": false,
          "notNull": false
        },
        "email": {
          "name": "email",
          "type": "text",
          "primaryKey": false,
          "notNull": false
        },
        "session_id": {
          "name": "session_id",
          "type": "text",
          "primaryKey": false,
          "notNull": false
        }
      },
      "indexes": {},
      "foreignKeys": {},
      "compositePrimaryKeys": {},
      "uniqueConstraints": {
        "testimonials_email_key": {
          "columns": [
            "email"
          ],
          "nullsNotDistinct": false,
          "name": "testimonials_email_key"
        }
      },
      "checkConstraints": {},
      "policies": {},
      "isRLSEnabled": false
    }
  },
  "enums": {},
  "schemas": {},
  "sequences": {},
  "roles": {},
  "policies": {},
  "views": {},
  "_meta": {
    "schemas": {},
    "tables": {},
    "columns": {}
  },
  "internal": {
    "tables": {}
  }
}